jlab_rucio_policy_package/__init__.py
jlab_rucio_policy_package/lfn2pfn.py
jlab_rucio_policy_package/permission.py
jlab_rucio_policy_package/schema.py
jlab_rucio_policy_package/scope.py
jlab_rucio_policy_package-0.0.1a5.dist-info/licenses/LICENSE
jlab_rucio_policy_package-0.0.1a5.dist-info/METADATA
jlab_rucio_policy_package-0.0.1a5.dist-info/WHEEL
jlab_rucio_policy_package-0.0.1a5.dist-info/top_level.txt
jlab_rucio_policy_package-0.0.1a5.dist-info/RECORD
