Metadata-Version: 2.4
Name: jlab-rucio-policy-package
Version: 0.0.1a5
Summary: Rucio policy package for the JLAB experiment
Author-email: JLAB <placeholder@placeholder.com>
License:                                  Apache License
Classifier: Programming Language :: Python :: 3
Classifier: Operating System :: OS Independent
Requires-Python: >=3.9
License-File: LICENSE
Dynamic: license-file
